queryboost/__init__.py
queryboost/auth.py
queryboost/queryboost.py
queryboost/stream.py
queryboost/config/__init__.py
queryboost/config/config.py
queryboost/exceptions/__init__.py
queryboost/exceptions/exceptions.py
queryboost/handlers/__init__.py
queryboost/handlers/base.py
queryboost/handlers/local.py
queryboost/handlers/s3.py
queryboost/types/__init__.py
queryboost/utils/__init__.py
queryboost/utils/data.py
queryboost/utils/prompt.py
queryboost-0.1.4.dist-info/METADATA
queryboost-0.1.4.dist-info/WHEEL
queryboost-0.1.4.dist-info/licenses/LICENSE
queryboost-0.1.4.dist-info/RECORD
