Metadata-Version: 2.3
Name: queryboost
Version: 0.1.4
Summary: The official Python client for the Queryboost API
Project-URL: Homepage, https://queryboost.com
Project-URL: Repository, https://github.com/queryboost/queryboost
Author-email: Johnson Kuan <johnson@queryboost.com>
Keywords: ai,batch,inference,queryboost,streaming
Classifier: Intended Audience :: Developers
Classifier: License :: OSI Approved :: Apache Software License
Classifier: Programming Language :: Python :: 3.12
Classifier: Programming Language :: Python :: 3.13
Classifier: Topic :: Software Development :: Libraries :: Python Modules
Requires-Python: >=3.12
Requires-Dist: boto3>=1.40.61
Requires-Dist: certifi>=2025.8.3
Requires-Dist: datasets>=4.1.1
Requires-Dist: more-itertools>=10.8.0
Requires-Dist: pyarrow>=21.0.0
Requires-Dist: tqdm>=4.67.1
